RoxiLib/RoxiCommunication.py
RoxiLib/RoxiStateHandler.py
RoxiLib/__init__.py
RoxiLib/bt_data.h
RoxiLib/libRoxi.dll
RoxiLib/library_version.h
RoxiLib/roxi_api_common.h
RoxiLib/roxi_api_wdk.h
RoxiLib-0.6.0.dist-info/METADATA
RoxiLib-0.6.0.dist-info/WHEEL
RoxiLib-0.6.0.dist-info/top_level.txt
RoxiLib-0.6.0.dist-info/RECORD
