Metadata-Version: 2.1
Name: RoxiLib
Version: 0.6.0
Summary: Python API for Roxi lib
Home-page: https://github.com/wavingroup/allinclusive_API
Author: Wavin T&I
Author-email: support@wavin.com
License: MIT
Classifier: Development Status :: 5 - Production/Stable
Classifier: License :: OSI Approved :: MIT License
Classifier: Programming Language :: Python
